azure_sfi_agent/AGENT_INSTRUCTIONS.md
azure_sfi_agent/__init__.py
azure_sfi_agent/server.py
azure_sfi_agent/scripts/attach-log-analytics.ps1
azure_sfi_agent/scripts/attach-nsp.ps1
azure_sfi_agent/scripts/check-log-analytics.ps1
azure_sfi_agent/scripts/check-nsp.ps1
azure_sfi_agent/scripts/create-resourcegroup.ps1
azure_sfi_agent/scripts/deploy-ai-foundry.ps1
azure_sfi_agent/scripts/deploy-ai-search.ps1
azure_sfi_agent/scripts/deploy-keyvault.ps1
azure_sfi_agent/scripts/deploy-log-analytics.ps1
azure_sfi_agent/scripts/deploy-nsp.ps1
azure_sfi_agent/scripts/deploy-openai.ps1
azure_sfi_agent/scripts/deploy-storage-account.ps1
azure_sfi_agent/scripts/list-permissions.ps1
azure_sfi_agent/scripts/list-resources.ps1
azure_sfi_agent/templates/ai-foundry.bicep
azure_sfi_agent/templates/ai-search.bicep
azure_sfi_agent/templates/azure-key-vaults.bicep
azure_sfi_agent/templates/azure-openai.bicep
azure_sfi_agent/templates/log-analytics.bicep
azure_sfi_agent/templates/nsp.bicep
azure_sfi_agent/templates/storage-account.bicep
azure_sfi_agent_test-1.0.1.dist-info/LICENSE
azure_sfi_agent_test-1.0.1.dist-info/METADATA
azure_sfi_agent_test-1.0.1.dist-info/WHEEL
azure_sfi_agent_test-1.0.1.dist-info/entry_points.txt
azure_sfi_agent_test-1.0.1.dist-info/top_level.txt
azure_sfi_agent_test-1.0.1.dist-info/RECORD
